Metadata-Version: 2.1
Name: OreoML
Version: 0.0.28
Summary: Provide an input CSV and a target field to predict, generate a model.
Home-page: https://github.com/harishsg99/OreoML
Author: Harish S.G
Author-email: harishsg99@gmail.com
License: MIT
Keywords: deep learning,tensorflow,keras,automl,xgboost
Platform: UNKNOWN
Requires-Python: >=3.5
